{
  "period": "Jan 1 - May 9, 2026",
  "drivers": 41,
  "miles": 454000,
  "labor": 744851.74,
  "fuel_tot": 364414.57,
  "ins_tot": 128624.45,
  "truck_tot": 258455.19,
  "trailer_tot": 116566.39,
  "truck_maint": 4848.81,
  "trail_maint": 3841.89,
  "storage": 30568.68,
  "uniforms": 7923.56,
  "total_revenue": 7717066.41,
  "carrier_pay": 3928706.57,
  "gross_profit": 3719687.98,
  "net_income": 521722.5,
  "revenue_ce": 5428492.06,
  "revenue_sf": 2007859.21,
  "revenue_di": 41527.33,
  "net_op_income": 445082.79,
  "days_in_period": 129,
  "extracted_at": "2026-05-11T16:05:34.560Z"
}